{
    "314155682033041408": {
        "id": "314155682033041408",
        "states": {
            "tm": false,
            "bcp": false,
            "election": true,
            "trivia": true
        },
        "prefixes": {
            "generic": "!",
            "nadeko": "."
        },
        "channels": {
            "announcements": "announcements",
            "bot": "spam",
            "bot2": "devs",
            "mod": "test-channel-in-use",
            "log": "comment-log",
            "join": "join",
            "leave": "lounge",
            "live": "live"
        },
        "colors": {
            "generic": 53380,
            "error": 15406156,
            "ratings": 9359868
        },
        "roles": {
            "admin": "admin",
            "bot": "Bot-In-Use",
            "muted": "muted",
            "unranked": "unranked",
            "league": "league",
            "arena": "arena",
            "beta": "verified",
            "livenotifications": "subs"
        },
        "acceptedlinkdomains": [
            "http://lichess.org",
            "http://www.chess.com",
            "http://bughousetest.com",
            "https://lichess.org",
            "https://www.chess.com",
            "https://bughousetest.com"
        ],
        "regions": [
            "Americas",
            "Europe",
            "Middle East / Africa",
            "Asia / Australia"
        ],
        "shadowbanned": [
            [
                "402122806063529984",
                false
            ]
        ],
        "trivia": {
            "players": {
                "373480715276517376": true,
                "185412969130229760": true
            }
        },
        "tickets": [
            {
                "id": "312485288150827010",
                "tag": "supunay#6696",
                "amount": "20",
                "reason": "for invitinig arsenic 33",
                "messageid": "468889094873808896"
            },
            {
                "id": "312485288150827010",
                "tag": "supunay#6696",
                "amount": "32",
                "reason": "for https://lichess.org/tournament/qUXhP7Hg",
                "messageid": "469173550591508490"
            },
            {
                "id": "312485288150827010",
                "tag": "supunay#6696",
                "amount": "32",
                "reason": "for https://lichess.org/tournament/qUXhP7Hg",
                "messageid": "469173550591508490"
            },
            {
                "id": "469747377327046663",
                "tag": "moonenaneBETA#6381",
                "amount": "100",
                "reason": "i want it",
                "messageid": "470144030672683008"
            },
            {
                "id": "469747377327046663",
                "tag": "moonenaneBETA#6381",
                "amount": "100000000000",
                "reason": "because i really want it",
                "messageid": "470144105205202944"
            },
            {
                "id": "469747377327046663",
                "tag": "moonenaneBETA#6381",
                "amount": "999999999999999999999999999999",
                "reason": "because i want it",
                "messageid": "470144182791569419"
            },
            {
                "id": "319901088557957122",
                "tag": "okei#1207",
                "amount": "20",
                "reason": "invited marlonc",
                "messageid": "470346202454687745"
            }
        ],
        "ticketsv2": [],
        "getplaying": {
            "390259605529427969": [
                "penguingim1",
                "jkthebullfrog",
                "mastertan",
                "littleplotkin",
                "jannlee",
                "thefinnisher",
                "mmichael",
                "xuanet",
                "yasser-seirawan"
            ]
        },
        "notify": {
            "185412969130229760": 1532129995175
        },
        "election": {
            "960": {
                "candidates": {
                    "Musickn#8622": 0,
                    "okei#1207": 0
                },
                "voters": {
                    "318333488946479105": [],
                    "319901088557957122": [
                        1532268573168,
                        "319901088557957122",
                        "409729432236982282"
                    ],
                    "334801525400666112": [],
                    "278941339809218561": [],
                    "326918898178064396": [],
                    "365105589715599360": [],
                    "280124361833316352": [],
                    "317767348566097930": [],
                    "425376766085824512": [],
                    "390497170626707457": [],
                    "179603851073028100": [],
                    "127657658697121793": [],
                    "341618941317349376": [],
                    "211569666991063040": [],
                    "303746725292539916": [],
                    "325736595980288010": [
                        1532267260333,
                        "319901088557957122",
                        "409729432236982282"
                    ],
                    "341611207062716418": [],
                    "312824560602841089": [],
                    "346485544848457728": [],
                    "353627177729785856": [],
                    "330193848137678848": [],
                    "409729432236982282": [],
                    "445589708362350593": [],
                    "444087170672754698": [],
                    "312485288150827010": [],
                    "151069850557480960": [],
                    "406477568317980674": [],
                    "425719814086983690": [],
                    "370357539931684865": [],
                    "387727799823368199": [
                        1532330298833,
                        "319901088557957122",
                        "409729432236982282"
                    ],
                    "258998411284447232": [],
                    "185412969130229760": [
                        1532266985876,
                        "319901088557957122",
                        "409729432236982282"
                    ],
                    "324082212146249730": [
                        1532303763152,
                        "319901088557957122",
                        "409729432236982282"
                    ],
                    "365177031224459264": [],
                    "293465140739964929": [
                        1532333865255,
                        "319901088557957122",
                        "409729432236982282"
                    ],
                    "317034686973214720": [
                        1532268802708,
                        "319901088557957122",
                        "409729432236982282"
                    ],
                    "391250711297392640": [],
                    "411340403871055872": [],
                    "163325840136863744": [
                        1532330053757,
                        "409729432236982282",
                        "319901088557957122"
                    ],
                    "189057217591377920": [],
                    "238054892227395584": [],
                    "356192671750029313": [],
                    "381241162121478164": [],
                    "123574379601723392": [],
                    "316064197425496064": [],
                    "367024352174145547": [],
                    "291630149655330817": [],
                    "282841374410407937": [
                        1532266476205,
                        "319901088557957122"
                    ]
                }
            },
            "zh": {
                "candidates": {
                    "titsinablender#1754": 0,
                    "Fumitoks#3763": 0,
                    "LegionDestroyer#1652": 0
                },
                "voters": {
                    "128940476282830848": [
                        1532266403299,
                        "447723359317262336",
                        "324082212146249730",
                        "319235482619740160"
                    ],
                    "349930835274629120": [],
                    "378628590075641866": [],
                    "318333488946479105": [],
                    "151196126748475394": [],
                    "458318569260974081": [],
                    "227521505137917964": [],
                    "319901088557957122": [
                        1532268547956,
                        "319235482619740160",
                        "324082212146249730",
                        "447723359317262336"
                    ],
                    "299119819985518592": [],
                    "323331814267682816": [],
                    "267767816847884299": [],
                    "334801525400666112": [],
                    "410999653035802636": [],
                    "333586342275710978": [
                        1532266415224,
                        "319235482619740160",
                        "324082212146249730"
                    ],
                    "447723359317262336": [
                        1532266419368,
                        "324082212146249730",
                        "447723359317262336"
                    ],
                    "278941339809218561": [],
                    "386649194582245380": [
                        1532267025471,
                        "324082212146249730",
                        "319235482619740160",
                        "447723359317262336"
                    ],
                    "326918898178064396": [],
                    "365105589715599360": [],
                    "280124361833316352": [],
                    "317767348566097930": [],
                    "340287144448884748": [
                        1532278706819,
                        "324082212146249730"
                    ],
                    "366653947907276810": [],
                    "425376766085824512": [],
                    "454390762185031691": [],
                    "390497170626707457": [],
                    "259383384109744138": [
                        1532266705250,
                        "324082212146249730",
                        "319235482619740160",
                        "447723359317262336"
                    ],
                    "229327425903788033": [
                        1532271951358,
                        "319901088557957122",
                        "324082212146249730",
                        "447723359317262336",
                        "319235482619740160"
                    ],
                    "127657658697121793": [],
                    "290049116900294656": [],
                    "388560143555624970": [],
                    "341618941317349376": [],
                    "211569666991063040": [],
                    "303746725292539916": [],
                    "325736595980288010": [
                        1532267281644,
                        "324082212146249730",
                        "319235482619740160",
                        "447723359317262336"
                    ],
                    "319235482619740160": [
                        1532269317133,
                        "319235482619740160"
                    ],
                    "168239196849438721": [],
                    "312824560602841089": [
                        1532335278276,
                        "319235482619740160",
                        "447723359317262336",
                        "blank"
                    ],
                    "346485544848457728": [],
                    "373833486164819970": [],
                    "428398365504438272": [
                        1532301203823,
                        "324082212146249730",
                        "319235482619740160",
                        "447723359317262336"
                    ],
                    "353627177729785856": [],
                    "330193848137678848": [
                        1532287408016,
                        "324082212146249730"
                    ],
                    "240786679873404938": [],
                    "166996362716512258": [],
                    "409729432236982282": [
                        1532268304675,
                        "319235482619740160",
                        "324082212146249730",
                        "447723359317262336"
                    ],
                    "445589708362350593": [],
                    "446604525847969792": [],
                    "373480715276517376": [
                        1532266544062,
                        "319901088557957122",
                        "319235482619740160"
                    ],
                    "444087170672754698": [],
                    "313522262429007873": [
                        1532266723712,
                        "324082212146249730",
                        "319235482619740160",
                        "447723359317262336"
                    ],
                    "312485288150827010": [],
                    "449995873133527040": [
                        1532300896575,
                        "319235482619740160",
                        "447723359317262336",
                        "324082212146249730"
                    ],
                    "151069850557480960": [],
                    "406477568317980674": [],
                    "370357539931684865": [],
                    "441155101466296330": [],
                    "387727799823368199": [
                        1532330317673,
                        "319235482619740160",
                        "447723359317262336"
                    ],
                    "258998411284447232": [],
                    "324082212146249730": [
                        1532303785988,
                        "447723359317262336",
                        "319235482619740160",
                        "324082212146249730"
                    ],
                    "414816252733685760": [],
                    "365177031224459264": [],
                    "459915928281284619": [],
                    "291123072919011348": [],
                    "293465140739964929": [
                        1532333928236,
                        "319235482619740160",
                        "447723359317262336"
                    ],
                    "118174734176223243": [],
                    "235057081814614017": [],
                    "317034686973214720": [
                        1532268818279,
                        "447723359317262336",
                        "324082212146249730",
                        "319235482619740160"
                    ],
                    "397704323976396803": [],
                    "391250711297392640": [],
                    "101143512812113920": [],
                    "339587935458557963": [],
                    "411340403871055872": [],
                    "163325840136863744": [
                        1532330076968,
                        "319235482619740160",
                        "447723359317262336"
                    ],
                    "189057217591377920": [],
                    "356192671750029313": [],
                    "414927367937589250": [],
                    "123574379601723392": [],
                    "353632747530485763": [],
                    "316064197425496064": [],
                    "363519664875372556": [
                        1532277045453,
                        "324082212146249730",
                        "447723359317262336",
                        "319235482619740160"
                    ],
                    "379344516785766410": [],
                    "367024352174145547": [],
                    "250054301559291905": [],
                    "214371770797522945": [],
                    "409099831072522241": [],
                    "282841374410407937": [],
                    "451223030157279232": [],
                    "185412969130229760": [
                        1532267064194,
                        "319235482619740160",
                        "324082212146249730",
                        "447723359317262336",
                        "319901088557957122"
                    ]
                }
            },
            "bug": {
                "candidates": {
                    "Gopnik#4031": 0,
                    "samoyd#2402": 0
                },
                "voters": {
                    "349930835274629120": [],
                    "378628590075641866": [],
                    "318333488946479105": [],
                    "151196126748475394": [],
                    "319901088557957122": [
                        1532268462648,
                        "319901088557957122",
                        "229327425903788033"
                    ],
                    "299119819985518592": [],
                    "323331814267682816": [],
                    "267767816847884299": [],
                    "334801525400666112": [],
                    "333586342275710978": [
                        1532266531363,
                        "319901088557957122",
                        "229327425903788033"
                    ],
                    "447723359317262336": [
                        1532266440896,
                        "317034686973214720"
                    ],
                    "278941339809218561": [],
                    "222113473549565952": [],
                    "326918898178064396": [],
                    "365105589715599360": [],
                    "317767348566097930": [],
                    "340287144448884748": [
                        1532278719526,
                        "229327425903788033"
                    ],
                    "366653947907276810": [],
                    "390497170626707457": [],
                    "259383384109744138": [
                        1532267029009,
                        "319901088557957122"
                    ],
                    "229327425903788033": [
                        1532271976150,
                        "229327425903788033",
                        "319901088557957122",
                        "317034686973214720"
                    ],
                    "290049116900294656": [],
                    "388560143555624970": [],
                    "341618941317349376": [],
                    "317375246388953089": [
                        1532268425746,
                        "blank"
                    ],
                    "211569666991063040": [
                        1532271047507,
                        "319901088557957122"
                    ],
                    "303746725292539916": [],
                    "325736595980288010": [
                        1532267377151,
                        "319901088557957122",
                        "229327425903788033",
                        "317034686973214720"
                    ],
                    "319235482619740160": [
                        1532271154205,
                        "325736595980288010"
                    ],
                    "341611207062716418": [],
                    "312824560602841089": [],
                    "346485544848457728": [],
                    "373833486164819970": [],
                    "353627177729785856": [],
                    "330193848137678848": [
                        1532287332407,
                        "229327425903788033"
                    ],
                    "409729432236982282": [],
                    "445589708362350593": [],
                    "446604525847969792": [],
                    "469747377327046663": [],
                    "373480715276517376": [
                        1532267171835,
                        "370357539931684865",
                        "319901088557957122",
                        "229327425903788033"
                    ],
                    "444087170672754698": [],
                    "313522262429007873": [],
                    "312485288150827010": [],
                    "151069850557480960": [],
                    "406477568317980674": [],
                    "425719814086983690": [],
                    "370357539931684865": [],
                    "441155101466296330": [],
                    "185412969130229760": [
                        1532267084328,
                        "229327425903788033",
                        "319901088557957122"
                    ],
                    "324082212146249730": [
                        1532303984446,
                        "229327425903788033",
                        "317034686973214720"
                    ],
                    "414816252733685760": [],
                    "365177031224459264": [],
                    "459915928281284619": [],
                    "293465140739964929": [
                        1532333945909,
                        "317034686973214720",
                        "229327425903788033"
                    ],
                    "118174734176223243": [],
                    "235057081814614017": [],
                    "317034686973214720": [
                        1532269026072,
                        "317034686973214720",
                        "229327425903788033"
                    ],
                    "391250711297392640": [],
                    "339587935458557963": [],
                    "163325840136863744": [
                        1532330100895,
                        "229327425903788033",
                        "317034686973214720"
                    ],
                    "189057217591377920": [],
                    "356192671750029313": [],
                    "123574379601723392": [],
                    "316064197425496064": [],
                    "363519664875372556": [
                        1532277197345,
                        "319901088557957122",
                        "317034686973214720",
                        "229327425903788033"
                    ],
                    "379344516785766410": [],
                    "367024352174145547": [],
                    "282841374410407937": [
                        1532266516154,
                        "229327425903788033"
                    ]
                },
                "okei#1207": 0,
                "Gopnik#4031": 0
            },
            "3-check": {
                "candidates": {
                    "Musickn#8622": 0,
                    "titsinablender#1754": 0
                },
                "voters": {
                    "318333488946479105": [],
                    "319901088557957122": [
                        1532268514854,
                        "409729432236982282",
                        "324082212146249730"
                    ],
                    "323331814267682816": [],
                    "267767816847884299": [],
                    "334801525400666112": [],
                    "410999653035802636": [],
                    "278941339809218561": [],
                    "326918898178064396": [],
                    "365105589715599360": [],
                    "179603851073028100": [],
                    "127657658697121793": [],
                    "388560143555624970": [],
                    "341618941317349376": [],
                    "211569666991063040": [],
                    "303746725292539916": [],
                    "325736595980288010": [
                        1532267392244,
                        "324082212146249730",
                        "409729432236982282"
                    ],
                    "168239196849438721": [],
                    "312824560602841089": [],
                    "346485544848457728": [],
                    "373833486164819970": [],
                    "353627177729785856": [],
                    "330193848137678848": [
                        1532287353999,
                        "324082212146249730"
                    ],
                    "409729432236982282": [],
                    "445589708362350593": [],
                    "446604525847969792": [],
                    "373480715276517376": [
                        1532266639340,
                        "409729432236982282"
                    ],
                    "444087170672754698": [],
                    "312485288150827010": [],
                    "151069850557480960": [],
                    "406477568317980674": [],
                    "370357539931684865": [],
                    "185412969130229760": [
                        1532267095352,
                        "409729432236982282",
                        "324082212146249730"
                    ],
                    "303609777756438529": [],
                    "324082212146249730": [],
                    "365177031224459264": [],
                    "293465140739964929": [
                        1532333969818,
                        "409729432236982282"
                    ],
                    "235057081814614017": [],
                    "317034686973214720": [
                        1532268838442,
                        "324082212146249730",
                        "409729432236982282"
                    ],
                    "391250711297392640": [],
                    "411340403871055872": [],
                    "163325840136863744": [
                        1532330117884,
                        "409729432236982282"
                    ],
                    "189057217591377920": [],
                    "238054892227395584": [],
                    "356192671750029313": [],
                    "373864486119014412": [],
                    "381241162121478164": [],
                    "123574379601723392": [],
                    "353632747530485763": [],
                    "316064197425496064": [],
                    "367024352174145547": [],
                    "442633705081667597": [],
                    "282841374410407937": []
                }
            },
            "4-player": {
                "voters": {
                    "318333488946479105": [],
                    "323331814267682816": [],
                    "334801525400666112": [],
                    "278941339809218561": [],
                    "326918898178064396": [],
                    "365105589715599360": [],
                    "341618941317349376": [],
                    "211569666991063040": [],
                    "303746725292539916": [],
                    "325736595980288010": [],
                    "312824560602841089": [],
                    "346485544848457728": [],
                    "373833486164819970": [],
                    "409729432236982282": [
                        1532272177931,
                        "346485544848457728"
                    ],
                    "444087170672754698": [],
                    "312485288150827010": [],
                    "151069850557480960": [],
                    "406477568317980674": [],
                    "425719814086983690": [],
                    "370357539931684865": [],
                    "387727799823368199": [
                        1532330374681,
                        "387727799823368199"
                    ],
                    "185412969130229760": [],
                    "324082212146249730": [],
                    "365177031224459264": [],
                    "235057081814614017": [],
                    "317034686973214720": [],
                    "391250711297392640": [],
                    "189057217591377920": [],
                    "238054892227395584": [],
                    "356192671750029313": [],
                    "367024352174145547": [],
                    "291630149655330817": []
                }
            },
            "anti": {
                "candidates": {
                    "Raven#9079": 0,
                    "Andrew#5850": 0
                },
                "voters": {
                    "318333488946479105": [],
                    "458318569260974081": [],
                    "377736677105467395": [],
                    "319901088557957122": [
                        1532268490350,
                        "330193848137678848"
                    ],
                    "323331814267682816": [],
                    "336399206061178880": [],
                    "267767816847884299": [],
                    "334801525400666112": [],
                    "133249411303211008": [
                        1532278799306,
                        "330193848137678848",
                        "303609777756438529"
                    ],
                    "278941339809218561": [],
                    "326918898178064396": [],
                    "365105589715599360": [],
                    "280124361833316352": [],
                    "179603851073028100": [],
                    "127657658697121793": [],
                    "341618941317349376": [],
                    "317375246388953089": [
                        1532268450352,
                        "330193848137678848",
                        "303609777756438529"
                    ],
                    "211569666991063040": [],
                    "303746725292539916": [],
                    "325736595980288010": [
                        1532267412862,
                        "330193848137678848",
                        "303609777756438529"
                    ],
                    "341611207062716418": [],
                    "312824560602841089": [
                        1532335239553,
                        "330193848137678848",
                        "303609777756438529",
                        "blank"
                    ],
                    "346485544848457728": [],
                    "373833486164819970": [],
                    "373803387705098250": [],
                    "428398365504438272": [
                        1532301219905,
                        "330193848137678848",
                        "303609777756438529"
                    ],
                    "330193848137678848": [
                        1532287293796,
                        "303609777756438529"
                    ],
                    "166996362716512258": [],
                    "409729432236982282": [
                        1532272201760,
                        "303609777756438529",
                        "330193848137678848"
                    ],
                    "446604525847969792": [],
                    "373480715276517376": [
                        1532266658335,
                        "303609777756438529",
                        "330193848137678848"
                    ],
                    "444087170672754698": [],
                    "313522262429007873": [],
                    "151069850557480960": [],
                    "406477568317980674": [],
                    "425719814086983690": [],
                    "373770768938434570": [],
                    "258998411284447232": [],
                    "185412969130229760": [
                        1532267234817,
                        "334801525400666112",
                        "330193848137678848",
                        "303609777756438529"
                    ],
                    "303609777756438529": [],
                    "324082212146249730": [],
                    "208101972686012417": [],
                    "365177031224459264": [],
                    "293465140739964929": [
                        1532334000026,
                        "330193848137678848",
                        "303609777756438529"
                    ],
                    "391250711297392640": [],
                    "101143512812113920": [],
                    "163325840136863744": [
                        1532330134251,
                        "330193848137678848",
                        "303609777756438529"
                    ],
                    "189057217591377920": [],
                    "238054892227395584": [],
                    "356192671750029313": [],
                    "373864486119014412": [],
                    "123574379601723392": [],
                    "291630149655330817": [],
                    "214371770797522945": [],
                    "282841374410407937": [],
                    "451223030157279232": []
                }
            },
            "horde": {
                "voters": {
                    "318333488946479105": [],
                    "458318569260974081": [],
                    "319901088557957122": [],
                    "323331814267682816": [],
                    "334801525400666112": [],
                    "278941339809218561": [],
                    "326918898178064396": [],
                    "365105589715599360": [],
                    "127657658697121793": [],
                    "341618941317349376": [],
                    "211569666991063040": [],
                    "303746725292539916": [],
                    "325736595980288010": [
                        1532269287245,
                        "375203600290414595"
                    ],
                    "312824560602841089": [],
                    "346485544848457728": [],
                    "428398365504438272": [],
                    "353627177729785856": [],
                    "330193848137678848": [],
                    "409729432236982282": [
                        1532272234549,
                        "375203600290414595"
                    ],
                    "445589708362350593": [],
                    "375203600290414595": [],
                    "444087170672754698": [],
                    "312485288150827010": [],
                    "151069850557480960": [],
                    "406477568317980674": [],
                    "425719814086983690": [],
                    "185412969130229760": [
                        1532267430101,
                        "375203600290414595"
                    ],
                    "324082212146249730": [],
                    "365177031224459264": [],
                    "293465140739964929": [],
                    "235057081814614017": [],
                    "101143512812113920": [],
                    "163325840136863744": [
                        1532330171376,
                        "375203600290414595"
                    ],
                    "189057217591377920": [],
                    "238054892227395584": [],
                    "356192671750029313": [],
                    "373864486119014412": [],
                    "381241162121478164": [],
                    "123574379601723392": [],
                    "291630149655330817": [],
                    "451223030157279232": []
                }
            },
            "s-chess": {
                "candidates": {
                    "schaker#9757": 0
                },
                "voters": {
                    "318333488946479105": [],
                    "319901088557957122": [
                        1532268202642,
                        "356192671750029313"
                    ],
                    "323331814267682816": [],
                    "267767816847884299": [],
                    "334801525400666112": [],
                    "278941339809218561": [],
                    "326918898178064396": [],
                    "365105589715599360": [],
                    "127657658697121793": [],
                    "341618941317349376": [],
                    "211569666991063040": [],
                    "303746725292539916": [],
                    "325736595980288010": [
                        1532267425405,
                        "356192671750029313"
                    ],
                    "319235482619740160": [
                        1532271031766,
                        "356192671750029313"
                    ],
                    "312824560602841089": [],
                    "346485544848457728": [],
                    "409729432236982282": [
                        1532272247190,
                        "356192671750029313"
                    ],
                    "445589708362350593": [],
                    "446604525847969792": [],
                    "444087170672754698": [],
                    "312485288150827010": [],
                    "151069850557480960": [],
                    "406477568317980674": [],
                    "425719814086983690": [],
                    "185412969130229760": [
                        1532267577250,
                        "356192671750029313"
                    ],
                    "303609777756438529": [],
                    "324082212146249730": [],
                    "365177031224459264": [],
                    "391250711297392640": [],
                    "163325840136863744": [
                        1532330189628,
                        "356192671750029313"
                    ],
                    "189057217591377920": [],
                    "238054892227395584": [],
                    "356192671750029313": [],
                    "123574379601723392": []
                }
            },
            "koth": {
                "candidates": {
                    "hauptschule#8263": 0,
                    "hidden _expert#8350": 0
                },
                "voters": {
                    "318333488946479105": [],
                    "458318569260974081": [],
                    "377736677105467395": [],
                    "299119819985518592": [],
                    "323331814267682816": [],
                    "267767816847884299": [],
                    "334801525400666112": [],
                    "133249411303211008": [
                        1532278822199,
                        "133249411303211008"
                    ],
                    "278941339809218561": [],
                    "326918898178064396": [],
                    "365105589715599360": [],
                    "127657658697121793": [],
                    "341618941317349376": [],
                    "211569666991063040": [],
                    "303746725292539916": [],
                    "325736595980288010": [
                        1532267439187,
                        "133249411303211008",
                        "341611207062716418"
                    ],
                    "341611207062716418": [],
                    "312824560602841089": [],
                    "346485544848457728": [],
                    "373833486164819970": [],
                    "428398365504438272": [
                        1532301314492,
                        "133249411303211008",
                        "341611207062716418"
                    ],
                    "353627177729785856": [],
                    "330193848137678848": [
                        1532287373925,
                        "133249411303211008"
                    ],
                    "409729432236982282": [
                        1532272273756,
                        "409729432236982282"
                    ],
                    "445589708362350593": [],
                    "375203600290414595": [],
                    "444087170672754698": [],
                    "313522262429007873": [],
                    "312485288150827010": [],
                    "151069850557480960": [],
                    "406477568317980674": [],
                    "425719814086983690": [],
                    "370357539931684865": [],
                    "387727799823368199": [
                        1532330338991,
                        "341611207062716418",
                        "133249411303211008"
                    ],
                    "185412969130229760": [
                        1532267591697,
                        "133249411303211008",
                        "341611207062716418"
                    ],
                    "303609777756438529": [],
                    "324082212146249730": [],
                    "365177031224459264": [],
                    "293465140739964929": [
                        1532334024662,
                        "341611207062716418",
                        "133249411303211008"
                    ],
                    "235057081814614017": [],
                    "391250711297392640": [],
                    "101143512812113920": [],
                    "411340403871055872": [],
                    "163325840136863744": [
                        1532330204157,
                        "133249411303211008",
                        "341611207062716418"
                    ],
                    "189057217591377920": [],
                    "238054892227395584": [],
                    "373864486119014412": [],
                    "123574379601723392": [],
                    "367024352174145547": [],
                    "291630149655330817": [],
                    "282841374410407937": [],
                    "451223030157279232": []
                }
            },
            "atomic": {
                "candidates": {
                    "ijh#0966": 0,
                    "supunay#6696": 0
                },
                "voters": {
                    "318333488946479105": [],
                    "458318569260974081": [],
                    "319901088557957122": [],
                    "323331814267682816": [],
                    "336399206061178880": [],
                    "267767816847884299": [],
                    "334801525400666112": [],
                    "333586342275710978": [
                        1532266560682,
                        "334801525400666112",
                        "312485288150827010"
                    ],
                    "278941339809218561": [
                        1532278839530,
                        "334801525400666112",
                        "312485288150827010"
                    ],
                    "326918898178064396": [],
                    "365105589715599360": [],
                    "454390762185031691": [],
                    "127657658697121793": [],
                    "341618941317349376": [],
                    "211569666991063040": [],
                    "303746725292539916": [],
                    "325736595980288010": [
                        1532267460224,
                        "312485288150827010",
                        "334801525400666112"
                    ],
                    "312824560602841089": [],
                    "346485544848457728": [],
                    "373833486164819970": [],
                    "373803387705098250": [],
                    "428398365504438272": [
                        1532301325184,
                        "312485288150827010",
                        "334801525400666112"
                    ],
                    "330193848137678848": [
                        1532287366176,
                        "334801525400666112"
                    ],
                    "409729432236982282": [
                        1532272308433,
                        "334801525400666112",
                        "312485288150827010"
                    ],
                    "446604525847969792": [],
                    "373480715276517376": [
                        1532266677371,
                        "334801525400666112"
                    ],
                    "444087170672754698": [],
                    "312485288150827010": [],
                    "151069850557480960": [],
                    "406477568317980674": [],
                    "425719814086983690": [],
                    "370357539931684865": [],
                    "387727799823368199": [
                        1532330352381,
                        "334801525400666112",
                        "312485288150827010"
                    ],
                    "258998411284447232": [],
                    "185412969130229760": [
                        1532261782083,
                        "334801525400666112",
                        "341618941317349376"
                    ],
                    "303609777756438529": [],
                    "324082212146249730": [],
                    "365177031224459264": [],
                    "293465140739964929": [
                        1532334044210,
                        "334801525400666112",
                        "312485288150827010"
                    ],
                    "235057081814614017": [],
                    "391250711297392640": [],
                    "101143512812113920": [],
                    "411340403871055872": [],
                    "163325840136863744": [
                        1532330220292,
                        "312485288150827010",
                        "334801525400666112"
                    ],
                    "189057217591377920": [],
                    "238054892227395584": [],
                    "373864486119014412": [],
                    "381241162121478164": [],
                    "123574379601723392": [],
                    "367024352174145547": [],
                    "291630149655330817": [],
                    "214371770797522945": [],
                    "282841374410407937": []
                }
            },
            "racing-kings": {
                "candidates": {
                    "FlyingFalcon#6391": 0
                },
                "voters": {
                    "318333488946479105": [],
                    "458318569260974081": [],
                    "323331814267682816": [],
                    "334801525400666112": [],
                    "278941339809218561": [],
                    "326918898178064396": [],
                    "365105589715599360": [],
                    "341618941317349376": [],
                    "211569666991063040": [],
                    "303746725292539916": [],
                    "325736595980288010": [
                        1532267476865,
                        "428398365504438272"
                    ],
                    "341611207062716418": [],
                    "312824560602841089": [],
                    "428398365504438272": [
                        1532301348224,
                        "428398365504438272"
                    ],
                    "330193848137678848": [],
                    "409729432236982282": [
                        1532272326839,
                        "blank"
                    ],
                    "446604525847969792": [],
                    "373480715276517376": [
                        1532266689544,
                        "428398365504438272"
                    ],
                    "444087170672754698": [],
                    "312485288150827010": [],
                    "151069850557480960": [],
                    "406477568317980674": [],
                    "185412969130229760": [
                        1532261226943,
                        "428398365504438272"
                    ],
                    "457948505495961601": [],
                    "324082212146249730": [],
                    "365177031224459264": [],
                    "293465140739964929": [],
                    "391250711297392640": [],
                    "163325840136863744": [
                        1532330233914,
                        "blank"
                    ],
                    "189057217591377920": [],
                    "238054892227395584": [],
                    "373864486119014412": [],
                    "381241162121478164": [],
                    "123574379601723392": [],
                    "265668525962690560": [],
                    "451223030157279232": []
                },
                "MasterTrap#3941": 0
            },
            "ultra": {
                "candidates": {
                    "samoyd#2402": 0,
                    "penguingm1#1997": 0
                },
                "voters": {
                    "318333488946479105": [],
                    "227521505137917964": [],
                    "319901088557957122": [
                        1532268136741,
                        "326918898178064396",
                        "229327425903788033"
                    ],
                    "323331814267682816": [],
                    "267767816847884299": [],
                    "334801525400666112": [],
                    "278941339809218561": [],
                    "386649194582245380": [
                        1532267040143,
                        "229327425903788033",
                        "326918898178064396"
                    ],
                    "326918898178064396": [],
                    "365105589715599360": [],
                    "229327425903788033": [
                        1532271984606,
                        "229327425903788033",
                        "326918898178064396"
                    ],
                    "127657658697121793": [],
                    "341618941317349376": [],
                    "211569666991063040": [],
                    "303746725292539916": [],
                    "325736595980288010": [
                        1532267490285,
                        "326918898178064396",
                        "229327425903788033"
                    ],
                    "312824560602841089": [
                        1532335256140,
                        "326918898178064396",
                        "229327425903788033",
                        "blank"
                    ],
                    "373833486164819970": [],
                    "330193848137678848": [
                        1532287382897,
                        "326918898178064396"
                    ],
                    "409729432236982282": [
                        1532272343806,
                        "326918898178064396",
                        "229327425903788033"
                    ],
                    "444087170672754698": [],
                    "313522262429007873": [
                        1532266760690,
                        "326918898178064396"
                    ],
                    "312485288150827010": [],
                    "151069850557480960": [],
                    "370357539931684865": [],
                    "185412969130229760": [
                        1532227997785,
                        "326918898178064396",
                        "229327425903788033"
                    ],
                    "303609777756438529": [],
                    "324082212146249730": [],
                    "293465140739964929": [
                        1532334068594,
                        "326918898178064396",
                        "229327425903788033"
                    ],
                    "235057081814614017": [],
                    "317034686973214720": [
                        1532269007055,
                        "blank"
                    ],
                    "391250711297392640": [],
                    "163325840136863744": [
                        1532330248251,
                        "326918898178064396",
                        "229327425903788033"
                    ],
                    "189057217591377920": [],
                    "373864486119014412": [],
                    "381241162121478164": [],
                    "123574379601723392": [],
                    "367024352174145547": []
                }
            },
            "voters": {
                "128940476282830848": [
                    "zh"
                ],
                "318333488946479105": [
                    "960",
                    "zh",
                    "bug",
                    "3-check",
                    "4-player",
                    "anti",
                    "horde",
                    "s-chess",
                    "koth",
                    "atomic",
                    "racing-kings",
                    "ultra"
                ],
                "319901088557957122": [
                    "960",
                    "zh",
                    "bug",
                    "3-check",
                    "anti",
                    "horde",
                    "s-chess",
                    "atomic",
                    "ultra"
                ],
                "334801525400666112": [
                    "960",
                    "zh",
                    "bug",
                    "3-check",
                    "4-player",
                    "anti",
                    "horde",
                    "s-chess",
                    "koth",
                    "atomic",
                    "racing-kings",
                    "ultra"
                ],
                "278941339809218561": [
                    "960",
                    "zh",
                    "bug",
                    "3-check",
                    "4-player",
                    "anti",
                    "horde",
                    "s-chess",
                    "koth",
                    "atomic",
                    "racing-kings",
                    "ultra"
                ],
                "326918898178064396": [
                    "960",
                    "zh",
                    "bug",
                    "3-check",
                    "4-player",
                    "anti",
                    "horde",
                    "s-chess",
                    "koth",
                    "atomic",
                    "racing-kings",
                    "ultra"
                ],
                "365105589715599360": [
                    "960",
                    "zh",
                    "bug",
                    "3-check",
                    "4-player",
                    "anti",
                    "horde",
                    "s-chess",
                    "koth",
                    "atomic",
                    "racing-kings",
                    "ultra"
                ],
                "280124361833316352": [
                    "960",
                    "zh",
                    "anti"
                ],
                "317767348566097930": [
                    "960",
                    "zh",
                    "bug"
                ],
                "425376766085824512": [
                    "960",
                    "zh"
                ],
                "390497170626707457": [
                    "960",
                    "zh",
                    "bug"
                ],
                "179603851073028100": [
                    "960",
                    "3-check",
                    "anti"
                ],
                "127657658697121793": [
                    "960",
                    "zh",
                    "3-check",
                    "anti",
                    "horde",
                    "s-chess",
                    "koth",
                    "atomic",
                    "ultra"
                ],
                "341618941317349376": [
                    "960",
                    "zh",
                    "bug",
                    "3-check",
                    "4-player",
                    "anti",
                    "horde",
                    "s-chess",
                    "koth",
                    "atomic",
                    "racing-kings",
                    "ultra"
                ],
                "211569666991063040": [
                    "960",
                    "zh",
                    "bug",
                    "3-check",
                    "4-player",
                    "anti",
                    "horde",
                    "s-chess",
                    "koth",
                    "atomic",
                    "racing-kings",
                    "ultra"
                ],
                "303746725292539916": [
                    "960",
                    "zh",
                    "bug",
                    "3-check",
                    "4-player",
                    "anti",
                    "horde",
                    "s-chess",
                    "koth",
                    "atomic",
                    "racing-kings",
                    "ultra"
                ],
                "325736595980288010": [
                    "960",
                    "zh",
                    "bug",
                    "3-check",
                    "4-player",
                    "anti",
                    "horde",
                    "s-chess",
                    "koth",
                    "atomic",
                    "racing-kings",
                    "ultra"
                ],
                "341611207062716418": [
                    "960",
                    "bug",
                    "anti",
                    "koth",
                    "racing-kings"
                ],
                "312824560602841089": [
                    "960",
                    "zh",
                    "bug",
                    "3-check",
                    "4-player",
                    "anti",
                    "horde",
                    "s-chess",
                    "koth",
                    "atomic",
                    "racing-kings",
                    "ultra"
                ],
                "346485544848457728": [
                    "960",
                    "zh",
                    "bug",
                    "3-check",
                    "4-player",
                    "anti",
                    "horde",
                    "s-chess",
                    "koth",
                    "atomic"
                ],
                "353627177729785856": [
                    "960",
                    "zh",
                    "bug",
                    "3-check",
                    "horde",
                    "koth"
                ],
                "330193848137678848": [
                    "960",
                    "zh",
                    "bug",
                    "3-check",
                    "anti",
                    "horde",
                    "koth",
                    "atomic",
                    "racing-kings",
                    "ultra"
                ],
                "409729432236982282": [
                    "960",
                    "zh",
                    "bug",
                    "3-check",
                    "4-player",
                    "anti",
                    "horde",
                    "s-chess",
                    "koth",
                    "atomic",
                    "racing-kings",
                    "ultra"
                ],
                "445589708362350593": [
                    "960",
                    "zh",
                    "bug",
                    "3-check",
                    "horde",
                    "s-chess",
                    "koth"
                ],
                "444087170672754698": [
                    "960",
                    "zh",
                    "bug",
                    "3-check",
                    "4-player",
                    "anti",
                    "horde",
                    "s-chess",
                    "koth",
                    "atomic",
                    "racing-kings",
                    "ultra"
                ],
                "312485288150827010": [
                    "960",
                    "zh",
                    "bug",
                    "3-check",
                    "4-player",
                    "horde",
                    "s-chess",
                    "koth",
                    "atomic",
                    "racing-kings",
                    "ultra"
                ],
                "151069850557480960": [
                    "960",
                    "zh",
                    "bug",
                    "3-check",
                    "4-player",
                    "anti",
                    "horde",
                    "s-chess",
                    "koth",
                    "atomic",
                    "racing-kings",
                    "ultra"
                ],
                "406477568317980674": [
                    "960",
                    "zh",
                    "bug",
                    "3-check",
                    "4-player",
                    "anti",
                    "horde",
                    "s-chess",
                    "koth",
                    "atomic",
                    "racing-kings"
                ],
                "425719814086983690": [
                    "960",
                    "bug",
                    "4-player",
                    "anti",
                    "horde",
                    "s-chess",
                    "koth",
                    "atomic"
                ],
                "370357539931684865": [
                    "960",
                    "zh",
                    "bug",
                    "3-check",
                    "4-player",
                    "koth",
                    "atomic",
                    "ultra"
                ],
                "387727799823368199": [
                    "960",
                    "zh",
                    "4-player",
                    "koth",
                    "atomic"
                ],
                "258998411284447232": [
                    "960",
                    "zh",
                    "anti",
                    "atomic"
                ],
                "185412969130229760": [
                    "960",
                    "zh",
                    "bug",
                    "3-check",
                    "4-player",
                    "anti",
                    "horde",
                    "s-chess",
                    "koth",
                    "atomic",
                    "racing-kings",
                    "ultra"
                ],
                "324082212146249730": [
                    "960",
                    "zh",
                    "bug",
                    "3-check",
                    "4-player",
                    "anti",
                    "horde",
                    "s-chess",
                    "koth",
                    "atomic",
                    "racing-kings",
                    "ultra"
                ],
                "365177031224459264": [
                    "960",
                    "zh",
                    "bug",
                    "3-check",
                    "4-player",
                    "anti",
                    "horde",
                    "s-chess",
                    "koth",
                    "atomic",
                    "racing-kings"
                ],
                "293465140739964929": [
                    "960",
                    "zh",
                    "bug",
                    "3-check",
                    "anti",
                    "horde",
                    "koth",
                    "atomic",
                    "racing-kings",
                    "ultra"
                ],
                "317034686973214720": [
                    "960",
                    "zh",
                    "bug",
                    "3-check",
                    "4-player",
                    "ultra"
                ],
                "391250711297392640": [
                    "960",
                    "zh",
                    "bug",
                    "3-check",
                    "4-player",
                    "anti",
                    "s-chess",
                    "koth",
                    "atomic",
                    "racing-kings",
                    "ultra"
                ],
                "411340403871055872": [
                    "960",
                    "zh",
                    "3-check",
                    "koth",
                    "atomic"
                ],
                "163325840136863744": [
                    "960",
                    "zh",
                    "bug",
                    "3-check",
                    "anti",
                    "horde",
                    "s-chess",
                    "koth",
                    "atomic",
                    "racing-kings",
                    "ultra"
                ],
                "189057217591377920": [
                    "960",
                    "zh",
                    "bug",
                    "3-check",
                    "4-player",
                    "anti",
                    "horde",
                    "s-chess",
                    "koth",
                    "atomic",
                    "racing-kings",
                    "ultra"
                ],
                "238054892227395584": [
                    "960",
                    "3-check",
                    "4-player",
                    "anti",
                    "horde",
                    "s-chess",
                    "koth",
                    "atomic",
                    "racing-kings"
                ],
                "356192671750029313": [
                    "960",
                    "zh",
                    "bug",
                    "3-check",
                    "4-player",
                    "anti",
                    "horde",
                    "s-chess"
                ],
                "381241162121478164": [
                    "960",
                    "3-check",
                    "horde",
                    "atomic",
                    "racing-kings",
                    "ultra"
                ],
                "123574379601723392": [
                    "960",
                    "zh",
                    "bug",
                    "3-check",
                    "anti",
                    "horde",
                    "s-chess",
                    "koth",
                    "atomic",
                    "racing-kings",
                    "ultra"
                ],
                "316064197425496064": [
                    "960",
                    "zh",
                    "bug",
                    "3-check"
                ],
                "367024352174145547": [
                    "960",
                    "zh",
                    "bug",
                    "3-check",
                    "4-player",
                    "koth",
                    "atomic",
                    "ultra"
                ],
                "291630149655330817": [
                    "960",
                    "4-player",
                    "anti",
                    "horde",
                    "koth",
                    "atomic"
                ],
                "282841374410407937": [
                    "960",
                    "zh",
                    "bug",
                    "3-check",
                    "anti",
                    "koth",
                    "atomic"
                ],
                "349930835274629120": [
                    "zh",
                    "bug"
                ],
                "378628590075641866": [
                    "zh",
                    "bug"
                ],
                "151196126748475394": [
                    "zh",
                    "bug"
                ],
                "458318569260974081": [
                    "zh",
                    "anti",
                    "horde",
                    "koth",
                    "atomic",
                    "racing-kings"
                ],
                "227521505137917964": [
                    "zh",
                    "ultra"
                ],
                "299119819985518592": [
                    "zh",
                    "bug",
                    "koth"
                ],
                "323331814267682816": [
                    "zh",
                    "bug",
                    "3-check",
                    "4-player",
                    "anti",
                    "horde",
                    "s-chess",
                    "koth",
                    "atomic",
                    "racing-kings",
                    "ultra"
                ],
                "267767816847884299": [
                    "zh",
                    "bug",
                    "3-check",
                    "anti",
                    "s-chess",
                    "koth",
                    "atomic",
                    "ultra"
                ],
                "410999653035802636": [
                    "zh",
                    "3-check"
                ],
                "333586342275710978": [
                    "zh",
                    "bug",
                    "atomic"
                ],
                "447723359317262336": [
                    "zh",
                    "bug"
                ],
                "386649194582245380": [
                    "zh",
                    "ultra"
                ],
                "340287144448884748": [
                    "zh",
                    "bug"
                ],
                "366653947907276810": [
                    "zh",
                    "bug"
                ],
                "454390762185031691": [
                    "zh",
                    "atomic"
                ],
                "259383384109744138": [
                    "zh",
                    "bug"
                ],
                "229327425903788033": [
                    "zh",
                    "bug",
                    "ultra"
                ],
                "290049116900294656": [
                    "zh",
                    "bug"
                ],
                "388560143555624970": [
                    "zh",
                    "bug",
                    "3-check"
                ],
                "319235482619740160": [
                    "zh",
                    "bug",
                    "s-chess"
                ],
                "168239196849438721": [
                    "zh",
                    "3-check"
                ],
                "373833486164819970": [
                    "zh",
                    "bug",
                    "3-check",
                    "4-player",
                    "anti",
                    "koth",
                    "atomic",
                    "ultra"
                ],
                "428398365504438272": [
                    "zh",
                    "anti",
                    "horde",
                    "koth",
                    "atomic",
                    "racing-kings"
                ],
                "240786679873404938": [
                    "zh"
                ],
                "166996362716512258": [
                    "zh",
                    "anti"
                ],
                "446604525847969792": [
                    "zh",
                    "bug",
                    "3-check",
                    "anti",
                    "s-chess",
                    "atomic",
                    "racing-kings"
                ],
                "373480715276517376": [
                    "zh",
                    "bug",
                    "3-check",
                    "anti",
                    "atomic",
                    "racing-kings"
                ],
                "313522262429007873": [
                    "zh",
                    "bug",
                    "anti",
                    "koth",
                    "ultra"
                ],
                "449995873133527040": [
                    "zh"
                ],
                "441155101466296330": [
                    "zh",
                    "bug"
                ],
                "414816252733685760": [
                    "zh",
                    "bug"
                ],
                "459915928281284619": [
                    "zh",
                    "bug"
                ],
                "291123072919011348": [
                    "zh"
                ],
                "118174734176223243": [
                    "zh",
                    "bug"
                ],
                "235057081814614017": [
                    "zh",
                    "bug",
                    "3-check",
                    "4-player",
                    "horde",
                    "koth",
                    "atomic",
                    "ultra"
                ],
                "397704323976396803": [
                    "zh"
                ],
                "101143512812113920": [
                    "zh",
                    "anti",
                    "horde",
                    "koth",
                    "atomic"
                ],
                "339587935458557963": [
                    "zh",
                    "bug"
                ],
                "414927367937589250": [
                    "zh"
                ],
                "353632747530485763": [
                    "zh",
                    "3-check"
                ],
                "363519664875372556": [
                    "zh",
                    "bug"
                ],
                "379344516785766410": [
                    "zh",
                    "bug"
                ],
                "250054301559291905": [
                    "zh"
                ],
                "214371770797522945": [
                    "zh",
                    "anti",
                    "atomic"
                ],
                "409099831072522241": [
                    "zh"
                ],
                "451223030157279232": [
                    "zh",
                    "anti",
                    "horde",
                    "koth",
                    "racing-kings"
                ],
                "222113473549565952": [
                    "bug"
                ],
                "317375246388953089": [
                    "bug",
                    "anti"
                ],
                "469747377327046663": [
                    "bug"
                ],
                "303609777756438529": [
                    "3-check",
                    "anti",
                    "s-chess",
                    "koth",
                    "atomic",
                    "ultra"
                ],
                "373864486119014412": [
                    "3-check",
                    "anti",
                    "horde",
                    "koth",
                    "atomic",
                    "racing-kings",
                    "ultra"
                ],
                "442633705081667597": [
                    "3-check"
                ],
                "377736677105467395": [
                    "anti",
                    "koth"
                ],
                "336399206061178880": [
                    "anti",
                    "atomic"
                ],
                "133249411303211008": [
                    "anti",
                    "koth"
                ],
                "373803387705098250": [
                    "anti",
                    "atomic"
                ],
                "373770768938434570": [
                    "anti"
                ],
                "208101972686012417": [
                    "anti"
                ],
                "375203600290414595": [
                    "horde",
                    "koth"
                ],
                "457948505495961601": [
                    "racing-kings"
                ],
                "265668525962690560": [
                    "racing-kings"
                ]
            }
        }
    }
}